[  
   {  
      "fields":{  
         "alpha2":"AF",
         "alpha3":"AFG",
         "name":"Afghanistan",
         "numeric":"004"
      },
      "model":"tracker.country",
      "pk":1
   },
   {  
      "fields":{  
         "alpha2":"AX",
         "alpha3":"ALA",
         "name":"\u00c5land Islands",
         "numeric":"248"
      },
      "model":"tracker.country",
      "pk":2
   },
   {  
      "fields":{  
         "alpha2":"AL",
         "alpha3":"ALB",
         "name":"Albania",
         "numeric":"008"
      },
      "model":"tracker.country",
      "pk":3
   },
   {  
      "fields":{  
         "alpha2":"DZ",
         "alpha3":"DZA",
         "name":"Algeria",
         "numeric":"012"
      },
      "model":"tracker.country",
      "pk":4
   },
   {  
      "fields":{  
         "alpha2":"AS",
         "alpha3":"ASM",
         "name":"American Samoa",
         "numeric":"016"
      },
      "model":"tracker.country",
      "pk":5
   },
   {  
      "fields":{  
         "alpha2":"AD",
         "alpha3":"AND",
         "name":"Andorra",
         "numeric":"020"
      },
      "model":"tracker.country",
      "pk":6
   },
   {  
      "fields":{  
         "alpha2":"AO",
         "alpha3":"AGO",
         "name":"Angola",
         "numeric":"024"
      },
      "model":"tracker.country",
      "pk":7
   },
   {  
      "fields":{  
         "alpha2":"AI",
         "alpha3":"AIA",
         "name":"Anguilla",
         "numeric":"660"
      },
      "model":"tracker.country",
      "pk":8
   },
   {  
      "fields":{  
         "alpha2":"AQ",
         "alpha3":"ATA",
         "name":"Antarctica",
         "numeric":"010"
      },
      "model":"tracker.country",
      "pk":9
   },
   {  
      "fields":{  
         "alpha2":"AG",
         "alpha3":"ATG",
         "name":"Antigua and Barbuda",
         "numeric":"028"
      },
      "model":"tracker.country",
      "pk":10
   },
   {  
      "fields":{  
         "alpha2":"AR",
         "alpha3":"ARG",
         "name":"Argentina",
         "numeric":"032"
      },
      "model":"tracker.country",
      "pk":11
   },
   {  
      "fields":{  
         "alpha2":"AM",
         "alpha3":"ARM",
         "name":"Armenia",
         "numeric":"051"
      },
      "model":"tracker.country",
      "pk":12
   },
   {  
      "fields":{  
         "alpha2":"AW",
         "alpha3":"ABW",
         "name":"Aruba",
         "numeric":"533"
      },
      "model":"tracker.country",
      "pk":13
   },
   {  
      "fields":{  
         "alpha2":"AU",
         "alpha3":"AUS",
         "name":"Australia",
         "numeric":"036"
      },
      "model":"tracker.country",
      "pk":14
   },
   {  
      "fields":{  
         "alpha2":"AT",
         "alpha3":"AUT",
         "name":"Austria",
         "numeric":"040"
      },
      "model":"tracker.country",
      "pk":15
   },
   {  
      "fields":{  
         "alpha2":"AZ",
         "alpha3":"AZE",
         "name":"Azerbaijan",
         "numeric":"031"
      },
      "model":"tracker.country",
      "pk":16
   },
   {  
      "fields":{  
         "alpha2":"BS",
         "alpha3":"BHS",
         "name":"Bahamas",
         "numeric":"044"
      },
      "model":"tracker.country",
      "pk":17
   },
   {  
      "fields":{  
         "alpha2":"BH",
         "alpha3":"BHR",
         "name":"Bahrain",
         "numeric":"048"
      },
      "model":"tracker.country",
      "pk":18
   },
   {  
      "fields":{  
         "alpha2":"BD",
         "alpha3":"BGD",
         "name":"Bangladesh",
         "numeric":"050"
      },
      "model":"tracker.country",
      "pk":19
   },
   {  
      "fields":{  
         "alpha2":"BB",
         "alpha3":"BRB",
         "name":"Barbados",
         "numeric":"052"
      },
      "model":"tracker.country",
      "pk":20
   },
   {  
      "fields":{  
         "alpha2":"BY",
         "alpha3":"BLR",
         "name":"Belarus",
         "numeric":"112"
      },
      "model":"tracker.country",
      "pk":21
   },
   {  
      "fields":{  
         "alpha2":"BE",
         "alpha3":"BEL",
         "name":"Belgium",
         "numeric":"056"
      },
      "model":"tracker.country",
      "pk":22
   },
   {  
      "fields":{  
         "alpha2":"BZ",
         "alpha3":"BLZ",
         "name":"Belize",
         "numeric":"084"
      },
      "model":"tracker.country",
      "pk":23
   },
   {  
      "fields":{  
         "alpha2":"BJ",
         "alpha3":"BEN",
         "name":"Benin",
         "numeric":"204"
      },
      "model":"tracker.country",
      "pk":24
   },
   {  
      "fields":{  
         "alpha2":"BM",
         "alpha3":"BMU",
         "name":"Bermuda",
         "numeric":"060"
      },
      "model":"tracker.country",
      "pk":25
   },
   {  
      "fields":{  
         "alpha2":"BT",
         "alpha3":"BTN",
         "name":"Bhutan",
         "numeric":"064"
      },
      "model":"tracker.country",
      "pk":26
   },
   {  
      "fields":{  
         "alpha2":"BO",
         "alpha3":"BOL",
         "name":"Bolivia (Plurinational State of)",
         "numeric":"068"
      },
      "model":"tracker.country",
      "pk":27
   },
   {  
      "fields":{  
         "alpha2":"BQ",
         "alpha3":"BES",
         "name":"Bonaire, Sint Eustatius and Saba",
         "numeric":"535"
      },
      "model":"tracker.country",
      "pk":28
   },
   {  
      "fields":{  
         "alpha2":"BA",
         "alpha3":"BIH",
         "name":"Bosnia and Herzegovina",
         "numeric":"070"
      },
      "model":"tracker.country",
      "pk":29
   },
   {  
      "fields":{  
         "alpha2":"BW",
         "alpha3":"BWA",
         "name":"Botswana",
         "numeric":"072"
      },
      "model":"tracker.country",
      "pk":30
   },
   {  
      "fields":{  
         "alpha2":"BV",
         "alpha3":"BVT",
         "name":"Bouvet Island",
         "numeric":"074"
      },
      "model":"tracker.country",
      "pk":31
   },
   {  
      "fields":{  
         "alpha2":"BR",
         "alpha3":"BRA",
         "name":"Brazil",
         "numeric":"076"
      },
      "model":"tracker.country",
      "pk":32
   },
   {  
      "fields":{  
         "alpha2":"IO",
         "alpha3":"IOT",
         "name":"British Indian Ocean Territory",
         "numeric":"086"
      },
      "model":"tracker.country",
      "pk":33
   },
   {  
      "fields":{  
         "alpha2":"BN",
         "alpha3":"BRN",
         "name":"Brunei Darussalam",
         "numeric":"096"
      },
      "model":"tracker.country",
      "pk":34
   },
   {  
      "fields":{  
         "alpha2":"BG",
         "alpha3":"BGR",
         "name":"Bulgaria",
         "numeric":"100"
      },
      "model":"tracker.country",
      "pk":35
   },
   {  
      "fields":{  
         "alpha2":"BF",
         "alpha3":"BFA",
         "name":"Burkina Faso",
         "numeric":"854"
      },
      "model":"tracker.country",
      "pk":36
   },
   {  
      "fields":{  
         "alpha2":"BI",
         "alpha3":"BDI",
         "name":"Burundi",
         "numeric":"108"
      },
      "model":"tracker.country",
      "pk":37
   },
   {  
      "fields":{  
         "alpha2":"KH",
         "alpha3":"KHM",
         "name":"Cambodia",
         "numeric":"116"
      },
      "model":"tracker.country",
      "pk":38
   },
   {  
      "fields":{  
         "alpha2":"CM",
         "alpha3":"CMR",
         "name":"Cameroon",
         "numeric":"120"
      },
      "model":"tracker.country",
      "pk":39
   },
   {  
      "fields":{  
         "alpha2":"CA",
         "alpha3":"CAN",
         "name":"Canada",
         "numeric":"124"
      },
      "model":"tracker.country",
      "pk":40
   },
   {  
      "fields":{  
         "alpha2":"CV",
         "alpha3":"CPV",
         "name":"Cabo Verde",
         "numeric":"132"
      },
      "model":"tracker.country",
      "pk":41
   },
   {  
      "fields":{  
         "alpha2":"KY",
         "alpha3":"CYM",
         "name":"Cayman Islands",
         "numeric":"136"
      },
      "model":"tracker.country",
      "pk":42
   },
   {  
      "fields":{  
         "alpha2":"CF",
         "alpha3":"CAF",
         "name":"Central African Republic",
         "numeric":"140"
      },
      "model":"tracker.country",
      "pk":43
   },
   {  
      "fields":{  
         "alpha2":"TD",
         "alpha3":"TCD",
         "name":"Chad",
         "numeric":"148"
      },
      "model":"tracker.country",
      "pk":44
   },
   {  
      "fields":{  
         "alpha2":"CL",
         "alpha3":"CHL",
         "name":"Chile",
         "numeric":"152"
      },
      "model":"tracker.country",
      "pk":45
   },
   {  
      "fields":{  
         "alpha2":"CN",
         "alpha3":"CHN",
         "name":"China",
         "numeric":"156"
      },
      "model":"tracker.country",
      "pk":46
   },
   {  
      "fields":{  
         "alpha2":"C2",
         "alpha3":"CN2",
         "name":"China (Paypal International Commerce)",
         "numeric":null
      },
      "model":"tracker.country",
      "pk":47
   },
   {  
      "fields":{  
         "alpha2":"CX",
         "alpha3":"CXR",
         "name":"Christmas Island",
         "numeric":"162"
      },
      "model":"tracker.country",
      "pk":48
   },
   {  
      "fields":{  
         "alpha2":"CC",
         "alpha3":"CCK",
         "name":"Cocos (Keeling) Islands",
         "numeric":"166"
      },
      "model":"tracker.country",
      "pk":49
   },
   {  
      "fields":{  
         "alpha2":"CO",
         "alpha3":"COL",
         "name":"Colombia",
         "numeric":"170"
      },
      "model":"tracker.country",
      "pk":50
   },
   {  
      "fields":{  
         "alpha2":"KM",
         "alpha3":"COM",
         "name":"Comoros",
         "numeric":"174"
      },
      "model":"tracker.country",
      "pk":51
   },
   {  
      "fields":{  
         "alpha2":"CG",
         "alpha3":"COG",
         "name":"Congo",
         "numeric":"178"
      },
      "model":"tracker.country",
      "pk":52
   },
   {  
      "fields":{  
         "alpha2":"CD",
         "alpha3":"COD",
         "name":"Congo (Democratic Republic of the)",
         "numeric":"180"
      },
      "model":"tracker.country",
      "pk":53
   },
   {  
      "fields":{  
         "alpha2":"CK",
         "alpha3":"COK",
         "name":"Cook Islands",
         "numeric":"184"
      },
      "model":"tracker.country",
      "pk":54
   },
   {  
      "fields":{  
         "alpha2":"CR",
         "alpha3":"CRI",
         "name":"Costa Rica",
         "numeric":"188"
      },
      "model":"tracker.country",
      "pk":55
   },
   {  
      "fields":{  
         "alpha2":"CI",
         "alpha3":"CIV",
         "name":"C\u00f4te d'Ivoire",
         "numeric":"384"
      },
      "model":"tracker.country",
      "pk":56
   },
   {  
      "fields":{  
         "alpha2":"HR",
         "alpha3":"HRV",
         "name":"Croatia",
         "numeric":"191"
      },
      "model":"tracker.country",
      "pk":57
   },
   {  
      "fields":{  
         "alpha2":"CU",
         "alpha3":"CUB",
         "name":"Cuba",
         "numeric":"192"
      },
      "model":"tracker.country",
      "pk":58
   },
   {  
      "fields":{  
         "alpha2":"CW",
         "alpha3":"CUW",
         "name":"Cura\u00e7ao",
         "numeric":"531"
      },
      "model":"tracker.country",
      "pk":59
   },
   {  
      "fields":{  
         "alpha2":"CY",
         "alpha3":"CYP",
         "name":"Cyprus",
         "numeric":"196"
      },
      "model":"tracker.country",
      "pk":60
   },
   {  
      "fields":{  
         "alpha2":"CZ",
         "alpha3":"CZE",
         "name":"Czech Republic",
         "numeric":"203"
      },
      "model":"tracker.country",
      "pk":61
   },
   {  
      "fields":{  
         "alpha2":"DK",
         "alpha3":"DNK",
         "name":"Denmark",
         "numeric":"208"
      },
      "model":"tracker.country",
      "pk":62
   },
   {  
      "fields":{  
         "alpha2":"DJ",
         "alpha3":"DJI",
         "name":"Djibouti",
         "numeric":"262"
      },
      "model":"tracker.country",
      "pk":63
   },
   {  
      "fields":{  
         "alpha2":"DM",
         "alpha3":"DMA",
         "name":"Dominica",
         "numeric":"212"
      },
      "model":"tracker.country",
      "pk":64
   },
   {  
      "fields":{  
         "alpha2":"DO",
         "alpha3":"DOM",
         "name":"Dominican Republic",
         "numeric":"214"
      },
      "model":"tracker.country",
      "pk":65
   },
   {  
      "fields":{  
         "alpha2":"EC",
         "alpha3":"ECU",
         "name":"Ecuador",
         "numeric":"218"
      },
      "model":"tracker.country",
      "pk":66
   },
   {  
      "fields":{  
         "alpha2":"EG",
         "alpha3":"EGY",
         "name":"Egypt",
         "numeric":"818"
      },
      "model":"tracker.country",
      "pk":67
   },
   {  
      "fields":{  
         "alpha2":"SV",
         "alpha3":"SLV",
         "name":"El Salvador",
         "numeric":"222"
      },
      "model":"tracker.country",
      "pk":68
   },
   {  
      "fields":{  
         "alpha2":"GQ",
         "alpha3":"GNQ",
         "name":"Equatorial Guinea",
         "numeric":"226"
      },
      "model":"tracker.country",
      "pk":69
   },
   {  
      "fields":{  
         "alpha2":"ER",
         "alpha3":"ERI",
         "name":"Eritrea",
         "numeric":"232"
      },
      "model":"tracker.country",
      "pk":70
   },
   {  
      "fields":{  
         "alpha2":"EE",
         "alpha3":"EST",
         "name":"Estonia",
         "numeric":"233"
      },
      "model":"tracker.country",
      "pk":71
   },
   {  
      "fields":{  
         "alpha2":"ET",
         "alpha3":"ETH",
         "name":"Ethiopia",
         "numeric":"231"
      },
      "model":"tracker.country",
      "pk":72
   },
   {  
      "fields":{  
         "alpha2":"FK",
         "alpha3":"FLK",
         "name":"Falkland Islands (Malvinas)",
         "numeric":"238"
      },
      "model":"tracker.country",
      "pk":73
   },
   {  
      "fields":{  
         "alpha2":"FO",
         "alpha3":"FRO",
         "name":"Faroe Islands",
         "numeric":"234"
      },
      "model":"tracker.country",
      "pk":74
   },
   {  
      "fields":{  
         "alpha2":"FJ",
         "alpha3":"FJI",
         "name":"Fiji",
         "numeric":"242"
      },
      "model":"tracker.country",
      "pk":75
   },
   {  
      "fields":{  
         "alpha2":"FI",
         "alpha3":"FIN",
         "name":"Finland",
         "numeric":"246"
      },
      "model":"tracker.country",
      "pk":76
   },
   {  
      "fields":{  
         "alpha2":"FR",
         "alpha3":"FRA",
         "name":"France",
         "numeric":"250"
      },
      "model":"tracker.country",
      "pk":77
   },
   {  
      "fields":{  
         "alpha2":"GF",
         "alpha3":"GUF",
         "name":"French Guiana",
         "numeric":"254"
      },
      "model":"tracker.country",
      "pk":78
   },
   {  
      "fields":{  
         "alpha2":"PF",
         "alpha3":"PYF",
         "name":"French Polynesia",
         "numeric":"258"
      },
      "model":"tracker.country",
      "pk":79
   },
   {  
      "fields":{  
         "alpha2":"TF",
         "alpha3":"ATF",
         "name":"French Southern Territories",
         "numeric":"260"
      },
      "model":"tracker.country",
      "pk":80
   },
   {  
      "fields":{  
         "alpha2":"GA",
         "alpha3":"GAB",
         "name":"Gabon",
         "numeric":"266"
      },
      "model":"tracker.country",
      "pk":81
   },
   {  
      "fields":{  
         "alpha2":"GM",
         "alpha3":"GMB",
         "name":"Gambia",
         "numeric":"270"
      },
      "model":"tracker.country",
      "pk":82
   },
   {  
      "fields":{  
         "alpha2":"GE",
         "alpha3":"GEO",
         "name":"Georgia",
         "numeric":"268"
      },
      "model":"tracker.country",
      "pk":83
   },
   {  
      "fields":{  
         "alpha2":"DE",
         "alpha3":"DEU",
         "name":"Germany",
         "numeric":"276"
      },
      "model":"tracker.country",
      "pk":84
   },
   {  
      "fields":{  
         "alpha2":"GH",
         "alpha3":"GHA",
         "name":"Ghana",
         "numeric":"288"
      },
      "model":"tracker.country",
      "pk":85
   },
   {  
      "fields":{  
         "alpha2":"GI",
         "alpha3":"GIB",
         "name":"Gibraltar",
         "numeric":"292"
      },
      "model":"tracker.country",
      "pk":86
   },
   {  
      "fields":{  
         "alpha2":"GR",
         "alpha3":"GRC",
         "name":"Greece",
         "numeric":"300"
      },
      "model":"tracker.country",
      "pk":87
   },
   {  
      "fields":{  
         "alpha2":"GL",
         "alpha3":"GRL",
         "name":"Greenland",
         "numeric":"304"
      },
      "model":"tracker.country",
      "pk":88
   },
   {  
      "fields":{  
         "alpha2":"GD",
         "alpha3":"GRD",
         "name":"Grenada",
         "numeric":"308"
      },
      "model":"tracker.country",
      "pk":89
   },
   {  
      "fields":{  
         "alpha2":"GP",
         "alpha3":"GLP",
         "name":"Guadeloupe",
         "numeric":"312"
      },
      "model":"tracker.country",
      "pk":90
   },
   {  
      "fields":{  
         "alpha2":"GU",
         "alpha3":"GUM",
         "name":"Guam",
         "numeric":"316"
      },
      "model":"tracker.country",
      "pk":91
   },
   {  
      "fields":{  
         "alpha2":"GT",
         "alpha3":"GTM",
         "name":"Guatemala",
         "numeric":"320"
      },
      "model":"tracker.country",
      "pk":92
   },
   {  
      "fields":{  
         "alpha2":"GG",
         "alpha3":"GGY",
         "name":"Guernsey",
         "numeric":"831"
      },
      "model":"tracker.country",
      "pk":93
   },
   {  
      "fields":{  
         "alpha2":"GN",
         "alpha3":"GIN",
         "name":"Guinea",
         "numeric":"324"
      },
      "model":"tracker.country",
      "pk":94
   },
   {  
      "fields":{  
         "alpha2":"GW",
         "alpha3":"GNB",
         "name":"Guinea-Bissau",
         "numeric":"624"
      },
      "model":"tracker.country",
      "pk":95
   },
   {  
      "fields":{  
         "alpha2":"GY",
         "alpha3":"GUY",
         "name":"Guyana",
         "numeric":"328"
      },
      "model":"tracker.country",
      "pk":96
   },
   {  
      "fields":{  
         "alpha2":"HT",
         "alpha3":"HTI",
         "name":"Haiti",
         "numeric":"332"
      },
      "model":"tracker.country",
      "pk":97
   },
   {  
      "fields":{  
         "alpha2":"HM",
         "alpha3":"HMD",
         "name":"Heard Island and McDonald Islands",
         "numeric":"334"
      },
      "model":"tracker.country",
      "pk":98
   },
   {  
      "fields":{  
         "alpha2":"VA",
         "alpha3":"VAT",
         "name":"Holy See",
         "numeric":"336"
      },
      "model":"tracker.country",
      "pk":99
   },
   {  
      "fields":{  
         "alpha2":"HN",
         "alpha3":"HND",
         "name":"Honduras",
         "numeric":"340"
      },
      "model":"tracker.country",
      "pk":100
   },
   {  
      "fields":{  
         "alpha2":"HK",
         "alpha3":"HKG",
         "name":"Hong Kong",
         "numeric":"344"
      },
      "model":"tracker.country",
      "pk":101
   },
   {  
      "fields":{  
         "alpha2":"HU",
         "alpha3":"HUN",
         "name":"Hungary",
         "numeric":"348"
      },
      "model":"tracker.country",
      "pk":102
   },
   {  
      "fields":{  
         "alpha2":"IS",
         "alpha3":"ISL",
         "name":"Iceland",
         "numeric":"352"
      },
      "model":"tracker.country",
      "pk":103
   },
   {  
      "fields":{  
         "alpha2":"IN",
         "alpha3":"IND",
         "name":"India",
         "numeric":"356"
      },
      "model":"tracker.country",
      "pk":104
   },
   {  
      "fields":{  
         "alpha2":"ID",
         "alpha3":"IDN",
         "name":"Indonesia",
         "numeric":"360"
      },
      "model":"tracker.country",
      "pk":105
   },
   {  
      "fields":{  
         "alpha2":"IR",
         "alpha3":"IRN",
         "name":"Iran (Islamic Republic of)",
         "numeric":"364"
      },
      "model":"tracker.country",
      "pk":106
   },
   {  
      "fields":{  
         "alpha2":"IQ",
         "alpha3":"IRQ",
         "name":"Iraq",
         "numeric":"368"
      },
      "model":"tracker.country",
      "pk":107
   },
   {  
      "fields":{  
         "alpha2":"IE",
         "alpha3":"IRL",
         "name":"Ireland",
         "numeric":"372"
      },
      "model":"tracker.country",
      "pk":108
   },
   {  
      "fields":{  
         "alpha2":"IM",
         "alpha3":"IMN",
         "name":"Isle of Man",
         "numeric":"833"
      },
      "model":"tracker.country",
      "pk":109
   },
   {  
      "fields":{  
         "alpha2":"IL",
         "alpha3":"ISR",
         "name":"Israel",
         "numeric":"376"
      },
      "model":"tracker.country",
      "pk":110
   },
   {  
      "fields":{  
         "alpha2":"IT",
         "alpha3":"ITA",
         "name":"Italy",
         "numeric":"380"
      },
      "model":"tracker.country",
      "pk":111
   },
   {  
      "fields":{  
         "alpha2":"JM",
         "alpha3":"JAM",
         "name":"Jamaica",
         "numeric":"388"
      },
      "model":"tracker.country",
      "pk":112
   },
   {  
      "fields":{  
         "alpha2":"JP",
         "alpha3":"JPN",
         "name":"Japan",
         "numeric":"392"
      },
      "model":"tracker.country",
      "pk":113
   },
   {  
      "fields":{  
         "alpha2":"JE",
         "alpha3":"JEY",
         "name":"Jersey",
         "numeric":"832"
      },
      "model":"tracker.country",
      "pk":114
   },
   {  
      "fields":{  
         "alpha2":"JO",
         "alpha3":"JOR",
         "name":"Jordan",
         "numeric":"400"
      },
      "model":"tracker.country",
      "pk":115
   },
   {  
      "fields":{  
         "alpha2":"KZ",
         "alpha3":"KAZ",
         "name":"Kazakhstan",
         "numeric":"398"
      },
      "model":"tracker.country",
      "pk":116
   },
   {  
      "fields":{  
         "alpha2":"KE",
         "alpha3":"KEN",
         "name":"Kenya",
         "numeric":"404"
      },
      "model":"tracker.country",
      "pk":117
   },
   {  
      "fields":{  
         "alpha2":"KI",
         "alpha3":"KIR",
         "name":"Kiribati",
         "numeric":"296"
      },
      "model":"tracker.country",
      "pk":118
   },
   {  
      "fields":{  
         "alpha2":"KP",
         "alpha3":"PRK",
         "name":"Korea (Democratic People's Republic of)",
         "numeric":"408"
      },
      "model":"tracker.country",
      "pk":119
   },
   {  
      "fields":{  
         "alpha2":"KR",
         "alpha3":"KOR",
         "name":"Korea (Republic of)",
         "numeric":"410"
      },
      "model":"tracker.country",
      "pk":120
   },
   {  
      "fields":{  
         "alpha2":"KW",
         "alpha3":"KWT",
         "name":"Kuwait",
         "numeric":"414"
      },
      "model":"tracker.country",
      "pk":121
   },
   {  
      "fields":{  
         "alpha2":"KG",
         "alpha3":"KGZ",
         "name":"Kyrgyzstan",
         "numeric":"417"
      },
      "model":"tracker.country",
      "pk":122
   },
   {  
      "fields":{  
         "alpha2":"LA",
         "alpha3":"LAO",
         "name":"Lao People's Democratic Republic",
         "numeric":"418"
      },
      "model":"tracker.country",
      "pk":123
   },
   {  
      "fields":{  
         "alpha2":"LV",
         "alpha3":"LVA",
         "name":"Latvia",
         "numeric":"428"
      },
      "model":"tracker.country",
      "pk":124
   },
   {  
      "fields":{  
         "alpha2":"LB",
         "alpha3":"LBN",
         "name":"Lebanon",
         "numeric":"422"
      },
      "model":"tracker.country",
      "pk":125
   },
   {  
      "fields":{  
         "alpha2":"LS",
         "alpha3":"LSO",
         "name":"Lesotho",
         "numeric":"426"
      },
      "model":"tracker.country",
      "pk":126
   },
   {  
      "fields":{  
         "alpha2":"LR",
         "alpha3":"LBR",
         "name":"Liberia",
         "numeric":"430"
      },
      "model":"tracker.country",
      "pk":127
   },
   {  
      "fields":{  
         "alpha2":"LY",
         "alpha3":"LBY",
         "name":"Libya",
         "numeric":"434"
      },
      "model":"tracker.country",
      "pk":128
   },
   {  
      "fields":{  
         "alpha2":"LI",
         "alpha3":"LIE",
         "name":"Liechtenstein",
         "numeric":"438"
      },
      "model":"tracker.country",
      "pk":129
   },
   {  
      "fields":{  
         "alpha2":"LT",
         "alpha3":"LTU",
         "name":"Lithuania",
         "numeric":"440"
      },
      "model":"tracker.country",
      "pk":130
   },
   {  
      "fields":{  
         "alpha2":"LU",
         "alpha3":"LUX",
         "name":"Luxembourg",
         "numeric":"442"
      },
      "model":"tracker.country",
      "pk":131
   },
   {  
      "fields":{  
         "alpha2":"MO",
         "alpha3":"MAC",
         "name":"Macao",
         "numeric":"446"
      },
      "model":"tracker.country",
      "pk":132
   },
   {  
      "fields":{  
         "alpha2":"MK",
         "alpha3":"MKD",
         "name":"Macedonia (the former Yugoslav Republic of)",
         "numeric":"807"
      },
      "model":"tracker.country",
      "pk":133
   },
   {  
      "fields":{  
         "alpha2":"MG",
         "alpha3":"MDG",
         "name":"Madagascar",
         "numeric":"450"
      },
      "model":"tracker.country",
      "pk":134
   },
   {  
      "fields":{  
         "alpha2":"MW",
         "alpha3":"MWI",
         "name":"Malawi",
         "numeric":"454"
      },
      "model":"tracker.country",
      "pk":135
   },
   {  
      "fields":{  
         "alpha2":"MY",
         "alpha3":"MYS",
         "name":"Malaysia",
         "numeric":"458"
      },
      "model":"tracker.country",
      "pk":136
   },
   {  
      "fields":{  
         "alpha2":"MV",
         "alpha3":"MDV",
         "name":"Maldives",
         "numeric":"462"
      },
      "model":"tracker.country",
      "pk":137
   },
   {  
      "fields":{  
         "alpha2":"ML",
         "alpha3":"MLI",
         "name":"Mali",
         "numeric":"466"
      },
      "model":"tracker.country",
      "pk":138
   },
   {  
      "fields":{  
         "alpha2":"MT",
         "alpha3":"MLT",
         "name":"Malta",
         "numeric":"470"
      },
      "model":"tracker.country",
      "pk":139
   },
   {  
      "fields":{  
         "alpha2":"MH",
         "alpha3":"MHL",
         "name":"Marshall Islands",
         "numeric":"584"
      },
      "model":"tracker.country",
      "pk":140
   },
   {  
      "fields":{  
         "alpha2":"MQ",
         "alpha3":"MTQ",
         "name":"Martinique",
         "numeric":"474"
      },
      "model":"tracker.country",
      "pk":141
   },
   {  
      "fields":{  
         "alpha2":"MR",
         "alpha3":"MRT",
         "name":"Mauritania",
         "numeric":"478"
      },
      "model":"tracker.country",
      "pk":142
   },
   {  
      "fields":{  
         "alpha2":"MU",
         "alpha3":"MUS",
         "name":"Mauritius",
         "numeric":"480"
      },
      "model":"tracker.country",
      "pk":143
   },
   {  
      "fields":{  
         "alpha2":"YT",
         "alpha3":"MYT",
         "name":"Mayotte",
         "numeric":"175"
      },
      "model":"tracker.country",
      "pk":144
   },
   {  
      "fields":{  
         "alpha2":"MX",
         "alpha3":"MEX",
         "name":"Mexico",
         "numeric":"484"
      },
      "model":"tracker.country",
      "pk":145
   },
   {  
      "fields":{  
         "alpha2":"FM",
         "alpha3":"FSM",
         "name":"Micronesia (Federated States of)",
         "numeric":"583"
      },
      "model":"tracker.country",
      "pk":146
   },
   {  
      "fields":{  
         "alpha2":"MD",
         "alpha3":"MDA",
         "name":"Moldova (Republic of)",
         "numeric":"498"
      },
      "model":"tracker.country",
      "pk":147
   },
   {  
      "fields":{  
         "alpha2":"MC",
         "alpha3":"MCO",
         "name":"Monaco",
         "numeric":"492"
      },
      "model":"tracker.country",
      "pk":148
   },
   {  
      "fields":{  
         "alpha2":"MN",
         "alpha3":"MNG",
         "name":"Mongolia",
         "numeric":"496"
      },
      "model":"tracker.country",
      "pk":149
   },
   {  
      "fields":{  
         "alpha2":"ME",
         "alpha3":"MNE",
         "name":"Montenegro",
         "numeric":"499"
      },
      "model":"tracker.country",
      "pk":150
   },
   {  
      "fields":{  
         "alpha2":"MS",
         "alpha3":"MSR",
         "name":"Montserrat",
         "numeric":"500"
      },
      "model":"tracker.country",
      "pk":151
   },
   {  
      "fields":{  
         "alpha2":"MA",
         "alpha3":"MAR",
         "name":"Morocco",
         "numeric":"504"
      },
      "model":"tracker.country",
      "pk":152
   },
   {  
      "fields":{  
         "alpha2":"MZ",
         "alpha3":"MOZ",
         "name":"Mozambique",
         "numeric":"508"
      },
      "model":"tracker.country",
      "pk":153
   },
   {  
      "fields":{  
         "alpha2":"MM",
         "alpha3":"MMR",
         "name":"Myanmar",
         "numeric":"104"
      },
      "model":"tracker.country",
      "pk":154
   },
   {  
      "fields":{  
         "alpha2":"NA",
         "alpha3":"NAM",
         "name":"Namibia",
         "numeric":"516"
      },
      "model":"tracker.country",
      "pk":155
   },
   {  
      "fields":{  
         "alpha2":"NR",
         "alpha3":"NRU",
         "name":"Nauru",
         "numeric":"520"
      },
      "model":"tracker.country",
      "pk":156
   },
   {  
      "fields":{  
         "alpha2":"NP",
         "alpha3":"NPL",
         "name":"Nepal",
         "numeric":"524"
      },
      "model":"tracker.country",
      "pk":157
   },
   {  
      "fields":{  
         "alpha2":"NL",
         "alpha3":"NLD",
         "name":"Netherlands",
         "numeric":"528"
      },
      "model":"tracker.country",
      "pk":158
   },
   {  
      "fields":{  
         "alpha2":"NC",
         "alpha3":"NCL",
         "name":"New Caledonia",
         "numeric":"540"
      },
      "model":"tracker.country",
      "pk":159
   },
   {  
      "fields":{  
         "alpha2":"NZ",
         "alpha3":"NZL",
         "name":"New Zealand",
         "numeric":"554"
      },
      "model":"tracker.country",
      "pk":160
   },
   {  
      "fields":{  
         "alpha2":"NI",
         "alpha3":"NIC",
         "name":"Nicaragua",
         "numeric":"558"
      },
      "model":"tracker.country",
      "pk":161
   },
   {  
      "fields":{  
         "alpha2":"NE",
         "alpha3":"NER",
         "name":"Niger",
         "numeric":"562"
      },
      "model":"tracker.country",
      "pk":162
   },
   {  
      "fields":{  
         "alpha2":"NG",
         "alpha3":"NGA",
         "name":"Nigeria",
         "numeric":"566"
      },
      "model":"tracker.country",
      "pk":163
   },
   {  
      "fields":{  
         "alpha2":"NU",
         "alpha3":"NIU",
         "name":"Niue",
         "numeric":"570"
      },
      "model":"tracker.country",
      "pk":164
   },
   {  
      "fields":{  
         "alpha2":"NF",
         "alpha3":"NFK",
         "name":"Norfolk Island",
         "numeric":"574"
      },
      "model":"tracker.country",
      "pk":165
   },
   {  
      "fields":{  
         "alpha2":"MP",
         "alpha3":"MNP",
         "name":"Northern Mariana Islands",
         "numeric":"580"
      },
      "model":"tracker.country",
      "pk":166
   },
   {  
      "fields":{  
         "alpha2":"NO",
         "alpha3":"NOR",
         "name":"Norway",
         "numeric":"578"
      },
      "model":"tracker.country",
      "pk":167
   },
   {  
      "fields":{  
         "alpha2":"OM",
         "alpha3":"OMN",
         "name":"Oman",
         "numeric":"512"
      },
      "model":"tracker.country",
      "pk":168
   },
   {  
      "fields":{  
         "alpha2":"PK",
         "alpha3":"PAK",
         "name":"Pakistan",
         "numeric":"586"
      },
      "model":"tracker.country",
      "pk":169
   },
   {  
      "fields":{  
         "alpha2":"PW",
         "alpha3":"PLW",
         "name":"Palau",
         "numeric":"585"
      },
      "model":"tracker.country",
      "pk":170
   },
   {  
      "fields":{  
         "alpha2":"PS",
         "alpha3":"PSE",
         "name":"Palestine, State of",
         "numeric":"275"
      },
      "model":"tracker.country",
      "pk":171
   },
   {  
      "fields":{  
         "alpha2":"PA",
         "alpha3":"PAN",
         "name":"Panama",
         "numeric":"591"
      },
      "model":"tracker.country",
      "pk":172
   },
   {  
      "fields":{  
         "alpha2":"PG",
         "alpha3":"PNG",
         "name":"Papua New Guinea",
         "numeric":"598"
      },
      "model":"tracker.country",
      "pk":173
   },
   {  
      "fields":{  
         "alpha2":"PY",
         "alpha3":"PRY",
         "name":"Paraguay",
         "numeric":"600"
      },
      "model":"tracker.country",
      "pk":174
   },
   {  
      "fields":{  
         "alpha2":"PE",
         "alpha3":"PER",
         "name":"Peru",
         "numeric":"604"
      },
      "model":"tracker.country",
      "pk":175
   },
   {  
      "fields":{  
         "alpha2":"PH",
         "alpha3":"PHL",
         "name":"Philippines",
         "numeric":"608"
      },
      "model":"tracker.country",
      "pk":176
   },
   {  
      "fields":{  
         "alpha2":"PN",
         "alpha3":"PCN",
         "name":"Pitcairn",
         "numeric":"612"
      },
      "model":"tracker.country",
      "pk":177
   },
   {  
      "fields":{  
         "alpha2":"PL",
         "alpha3":"POL",
         "name":"Poland",
         "numeric":"616"
      },
      "model":"tracker.country",
      "pk":178
   },
   {  
      "fields":{  
         "alpha2":"PT",
         "alpha3":"PRT",
         "name":"Portugal",
         "numeric":"620"
      },
      "model":"tracker.country",
      "pk":179
   },
   {  
      "fields":{  
         "alpha2":"PR",
         "alpha3":"PRI",
         "name":"Puerto Rico",
         "numeric":"630"
      },
      "model":"tracker.country",
      "pk":180
   },
   {  
      "fields":{  
         "alpha2":"QA",
         "alpha3":"QAT",
         "name":"Qatar",
         "numeric":"634"
      },
      "model":"tracker.country",
      "pk":181
   },
   {  
      "fields":{  
         "alpha2":"RE",
         "alpha3":"REU",
         "name":"R\u00e9union",
         "numeric":"638"
      },
      "model":"tracker.country",
      "pk":182
   },
   {  
      "fields":{  
         "alpha2":"RO",
         "alpha3":"ROU",
         "name":"Romania",
         "numeric":"642"
      },
      "model":"tracker.country",
      "pk":183
   },
   {  
      "fields":{  
         "alpha2":"RU",
         "alpha3":"RUS",
         "name":"Russian Federation",
         "numeric":"643"
      },
      "model":"tracker.country",
      "pk":184
   },
   {  
      "fields":{  
         "alpha2":"RW",
         "alpha3":"RWA",
         "name":"Rwanda",
         "numeric":"646"
      },
      "model":"tracker.country",
      "pk":185
   },
   {  
      "fields":{  
         "alpha2":"BL",
         "alpha3":"BLM",
         "name":"Saint Barth\u00e9lemy",
         "numeric":"652"
      },
      "model":"tracker.country",
      "pk":186
   },
   {  
      "fields":{  
         "alpha2":"SH",
         "alpha3":"SHN",
         "name":"Saint Helena, Ascension and Tristan da Cunha",
         "numeric":"654"
      },
      "model":"tracker.country",
      "pk":187
   },
   {  
      "fields":{  
         "alpha2":"KN",
         "alpha3":"KNA",
         "name":"Saint Kitts and Nevis",
         "numeric":"659"
      },
      "model":"tracker.country",
      "pk":188
   },
   {  
      "fields":{  
         "alpha2":"LC",
         "alpha3":"LCA",
         "name":"Saint Lucia",
         "numeric":"662"
      },
      "model":"tracker.country",
      "pk":189
   },
   {  
      "fields":{  
         "alpha2":"MF",
         "alpha3":"MAF",
         "name":"Saint Martin (French part)",
         "numeric":"663"
      },
      "model":"tracker.country",
      "pk":190
   },
   {  
      "fields":{  
         "alpha2":"PM",
         "alpha3":"SPM",
         "name":"Saint Pierre and Miquelon",
         "numeric":"666"
      },
      "model":"tracker.country",
      "pk":191
   },
   {  
      "fields":{  
         "alpha2":"VC",
         "alpha3":"VCT",
         "name":"Saint Vincent and the Grenadines",
         "numeric":"670"
      },
      "model":"tracker.country",
      "pk":192
   },
   {  
      "fields":{  
         "alpha2":"WS",
         "alpha3":"WSM",
         "name":"Samoa",
         "numeric":"882"
      },
      "model":"tracker.country",
      "pk":193
   },
   {  
      "fields":{  
         "alpha2":"SM",
         "alpha3":"SMR",
         "name":"San Marino",
         "numeric":"674"
      },
      "model":"tracker.country",
      "pk":194
   },
   {  
      "fields":{  
         "alpha2":"ST",
         "alpha3":"STP",
         "name":"Sao Tome and Principe",
         "numeric":"678"
      },
      "model":"tracker.country",
      "pk":195
   },
   {  
      "fields":{  
         "alpha2":"SA",
         "alpha3":"SAU",
         "name":"Saudi Arabia",
         "numeric":"682"
      },
      "model":"tracker.country",
      "pk":196
   },
   {  
      "fields":{  
         "alpha2":"SN",
         "alpha3":"SEN",
         "name":"Senegal",
         "numeric":"686"
      },
      "model":"tracker.country",
      "pk":197
   },
   {  
      "fields":{  
         "alpha2":"RS",
         "alpha3":"SRB",
         "name":"Serbia",
         "numeric":"688"
      },
      "model":"tracker.country",
      "pk":198
   },
   {  
      "fields":{  
         "alpha2":"SC",
         "alpha3":"SYC",
         "name":"Seychelles",
         "numeric":"690"
      },
      "model":"tracker.country",
      "pk":199
   },
   {  
      "fields":{  
         "alpha2":"SL",
         "alpha3":"SLE",
         "name":"Sierra Leone",
         "numeric":"694"
      },
      "model":"tracker.country",
      "pk":200
   },
   {  
      "fields":{  
         "alpha2":"SG",
         "alpha3":"SGP",
         "name":"Singapore",
         "numeric":"702"
      },
      "model":"tracker.country",
      "pk":201
   },
   {  
      "fields":{  
         "alpha2":"SX",
         "alpha3":"SXM",
         "name":"Sint Maarten (Dutch part)",
         "numeric":"534"
      },
      "model":"tracker.country",
      "pk":202
   },
   {  
      "fields":{  
         "alpha2":"SK",
         "alpha3":"SVK",
         "name":"Slovakia",
         "numeric":"703"
      },
      "model":"tracker.country",
      "pk":203
   },
   {  
      "fields":{  
         "alpha2":"SI",
         "alpha3":"SVN",
         "name":"Slovenia",
         "numeric":"705"
      },
      "model":"tracker.country",
      "pk":204
   },
   {  
      "fields":{  
         "alpha2":"SB",
         "alpha3":"SLB",
         "name":"Solomon Islands",
         "numeric":"090"
      },
      "model":"tracker.country",
      "pk":205
   },
   {  
      "fields":{  
         "alpha2":"SO",
         "alpha3":"SOM",
         "name":"Somalia",
         "numeric":"706"
      },
      "model":"tracker.country",
      "pk":206
   },
   {  
      "fields":{  
         "alpha2":"ZA",
         "alpha3":"ZAF",
         "name":"South Africa",
         "numeric":"710"
      },
      "model":"tracker.country",
      "pk":207
   },
   {  
      "fields":{  
         "alpha2":"GS",
         "alpha3":"SGS",
         "name":"South Georgia and the South Sandwich Islands",
         "numeric":"239"
      },
      "model":"tracker.country",
      "pk":208
   },
   {  
      "fields":{  
         "alpha2":"SS",
         "alpha3":"SSD",
         "name":"South Sudan",
         "numeric":"728"
      },
      "model":"tracker.country",
      "pk":209
   },
   {  
      "fields":{  
         "alpha2":"ES",
         "alpha3":"ESP",
         "name":"Spain",
         "numeric":"724"
      },
      "model":"tracker.country",
      "pk":210
   },
   {  
      "fields":{  
         "alpha2":"LK",
         "alpha3":"LKA",
         "name":"Sri Lanka",
         "numeric":"144"
      },
      "model":"tracker.country",
      "pk":211
   },
   {  
      "fields":{  
         "alpha2":"SD",
         "alpha3":"SDN",
         "name":"Sudan",
         "numeric":"729"
      },
      "model":"tracker.country",
      "pk":212
   },
   {  
      "fields":{  
         "alpha2":"SR",
         "alpha3":"SUR",
         "name":"Suriname",
         "numeric":"740"
      },
      "model":"tracker.country",
      "pk":213
   },
   {  
      "fields":{  
         "alpha2":"SJ",
         "alpha3":"SJM",
         "name":"Svalbard and Jan Mayen",
         "numeric":"744"
      },
      "model":"tracker.country",
      "pk":214
   },
   {  
      "fields":{  
         "alpha2":"SZ",
         "alpha3":"SWZ",
         "name":"Swaziland",
         "numeric":"748"
      },
      "model":"tracker.country",
      "pk":215
   },
   {  
      "fields":{  
         "alpha2":"SE",
         "alpha3":"SWE",
         "name":"Sweden",
         "numeric":"752"
      },
      "model":"tracker.country",
      "pk":216
   },
   {  
      "fields":{  
         "alpha2":"CH",
         "alpha3":"CHE",
         "name":"Switzerland",
         "numeric":"756"
      },
      "model":"tracker.country",
      "pk":217
   },
   {  
      "fields":{  
         "alpha2":"SY",
         "alpha3":"SYR",
         "name":"Syrian Arab Republic",
         "numeric":"760"
      },
      "model":"tracker.country",
      "pk":218
   },
   {  
      "fields":{  
         "alpha2":"TW",
         "alpha3":"TWN",
         "name":"Taiwan, Province of China[a]",
         "numeric":"158"
      },
      "model":"tracker.country",
      "pk":219
   },
   {  
      "fields":{  
         "alpha2":"TJ",
         "alpha3":"TJK",
         "name":"Tajikistan",
         "numeric":"762"
      },
      "model":"tracker.country",
      "pk":220
   },
   {  
      "fields":{  
         "alpha2":"TZ",
         "alpha3":"TZA",
         "name":"Tanzania, United Republic of",
         "numeric":"834"
      },
      "model":"tracker.country",
      "pk":221
   },
   {  
      "fields":{  
         "alpha2":"TH",
         "alpha3":"THA",
         "name":"Thailand",
         "numeric":"764"
      },
      "model":"tracker.country",
      "pk":222
   },
   {  
      "fields":{  
         "alpha2":"TL",
         "alpha3":"TLS",
         "name":"Timor-Leste",
         "numeric":"626"
      },
      "model":"tracker.country",
      "pk":223
   },
   {  
      "fields":{  
         "alpha2":"TG",
         "alpha3":"TGO",
         "name":"Togo",
         "numeric":"768"
      },
      "model":"tracker.country",
      "pk":224
   },
   {  
      "fields":{  
         "alpha2":"TK",
         "alpha3":"TKL",
         "name":"Tokelau",
         "numeric":"772"
      },
      "model":"tracker.country",
      "pk":225
   },
   {  
      "fields":{  
         "alpha2":"TO",
         "alpha3":"TON",
         "name":"Tonga",
         "numeric":"776"
      },
      "model":"tracker.country",
      "pk":226
   },
   {  
      "fields":{  
         "alpha2":"TT",
         "alpha3":"TTO",
         "name":"Trinidad and Tobago",
         "numeric":"780"
      },
      "model":"tracker.country",
      "pk":227
   },
   {  
      "fields":{  
         "alpha2":"TN",
         "alpha3":"TUN",
         "name":"Tunisia",
         "numeric":"788"
      },
      "model":"tracker.country",
      "pk":228
   },
   {  
      "fields":{  
         "alpha2":"TR",
         "alpha3":"TUR",
         "name":"Turkey",
         "numeric":"792"
      },
      "model":"tracker.country",
      "pk":229
   },
   {  
      "fields":{  
         "alpha2":"TM",
         "alpha3":"TKM",
         "name":"Turkmenistan",
         "numeric":"795"
      },
      "model":"tracker.country",
      "pk":230
   },
   {  
      "fields":{  
         "alpha2":"TC",
         "alpha3":"TCA",
         "name":"Turks and Caicos Islands",
         "numeric":"796"
      },
      "model":"tracker.country",
      "pk":231
   },
   {  
      "fields":{  
         "alpha2":"TV",
         "alpha3":"TUV",
         "name":"Tuvalu",
         "numeric":"798"
      },
      "model":"tracker.country",
      "pk":232
   },
   {  
      "fields":{  
         "alpha2":"UG",
         "alpha3":"UGA",
         "name":"Uganda",
         "numeric":"800"
      },
      "model":"tracker.country",
      "pk":233
   },
   {  
      "fields":{  
         "alpha2":"UA",
         "alpha3":"UKR",
         "name":"Ukraine",
         "numeric":"804"
      },
      "model":"tracker.country",
      "pk":234
   },
   {  
      "fields":{  
         "alpha2":"AE",
         "alpha3":"ARE",
         "name":"United Arab Emirates",
         "numeric":"784"
      },
      "model":"tracker.country",
      "pk":235
   },
   {  
      "fields":{  
         "alpha2":"GB",
         "alpha3":"GBR",
         "name":"United Kingdom of Great Britain and Northern Ireland",
         "numeric":"826"
      },
      "model":"tracker.country",
      "pk":236
   },
   {  
      "fields":{  
         "alpha2":"US",
         "alpha3":"USA",
         "name":"United States of America",
         "numeric":"840"
      },
      "model":"tracker.country",
      "pk":237
   },
   {  
      "fields":{  
         "alpha2":"UM",
         "alpha3":"UMI",
         "name":"United States Minor Outlying Islands",
         "numeric":"581"
      },
      "model":"tracker.country",
      "pk":238
   },
   {  
      "fields":{  
         "alpha2":"UY",
         "alpha3":"URY",
         "name":"Uruguay",
         "numeric":"858"
      },
      "model":"tracker.country",
      "pk":239
   },
   {  
      "fields":{  
         "alpha2":"UZ",
         "alpha3":"UZB",
         "name":"Uzbekistan",
         "numeric":"860"
      },
      "model":"tracker.country",
      "pk":240
   },
   {  
      "fields":{  
         "alpha2":"VU",
         "alpha3":"VUT",
         "name":"Vanuatu",
         "numeric":"548"
      },
      "model":"tracker.country",
      "pk":241
   },
   {  
      "fields":{  
         "alpha2":"VE",
         "alpha3":"VEN",
         "name":"Venezuela (Bolivarian Republic of)",
         "numeric":"862"
      },
      "model":"tracker.country",
      "pk":242
   },
   {  
      "fields":{  
         "alpha2":"VN",
         "alpha3":"VNM",
         "name":"Viet Nam",
         "numeric":"704"
      },
      "model":"tracker.country",
      "pk":243
   },
   {  
      "fields":{  
         "alpha2":"VG",
         "alpha3":"VGB",
         "name":"Virgin Islands (British)",
         "numeric":"092"
      },
      "model":"tracker.country",
      "pk":244
   },
   {  
      "fields":{  
         "alpha2":"VI",
         "alpha3":"VIR",
         "name":"Virgin Islands (U.S.)",
         "numeric":"850"
      },
      "model":"tracker.country",
      "pk":245
   },
   {  
      "fields":{  
         "alpha2":"WF",
         "alpha3":"WLF",
         "name":"Wallis and Futuna",
         "numeric":"876"
      },
      "model":"tracker.country",
      "pk":246
   },
   {  
      "fields":{  
         "alpha2":"EH",
         "alpha3":"ESH",
         "name":"Western Sahara",
         "numeric":"732"
      },
      "model":"tracker.country",
      "pk":247
   },
   {  
      "fields":{  
         "alpha2":"YE",
         "alpha3":"YEM",
         "name":"Yemen",
         "numeric":"887"
      },
      "model":"tracker.country",
      "pk":248
   },
   {  
      "fields":{  
         "alpha2":"ZM",
         "alpha3":"ZMB",
         "name":"Zambia",
         "numeric":"894"
      },
      "model":"tracker.country",
      "pk":249
   },
   {  
      "fields":{  
         "alpha2":"ZW",
         "alpha3":"ZWE",
         "name":"Zimbabwe",
         "numeric":"716"
      },
      "model":"tracker.country",
      "pk":250
   }
]
